setup.cfg
setup.py
BOASM.egg-info/PKG-INFO
BOASM.egg-info/SOURCES.txt
BOASM.egg-info/dependency_links.txt
BOASM.egg-info/top_level.txt
boasm/__init__.py
boasm/utils.py