Metadata-Version: 1.0
Name: BOASM
Version: 0.1.0
Summary: Budgeted Online Active Surrogate Modeling
Home-page: https://boasm.github.io/
Author: Amir Sani
Author-email: reachme@amirsani.com
License: CC BY-NC-SA 4.0
Platform: UNKNOWN
